sbatchman/__init__.py
sbatchman/cli.py
sbatchman/exceptions.py
sbatchman/config/global_config.py
sbatchman/config/project_config.py
sbatchman/core/__init__.py
sbatchman/core/config_manager.py
sbatchman/core/job.py
sbatchman/core/jobs_manager.py
sbatchman/core/launcher.py
sbatchman/core/status.py
sbatchman/schedulers/__init.py
sbatchman/schedulers/base.py
sbatchman/schedulers/local.py
sbatchman/schedulers/pbs.py
sbatchman/schedulers/slurm.py
sbatchman/tui/jobs_screen.py
sbatchman/tui/log_screen.py
sbatchman/tui/style.tcss
sbatchman/tui/tui.py
sbatchman-0.9.7.dist-info/METADATA
sbatchman-0.9.7.dist-info/WHEEL
sbatchman-0.9.7.dist-info/entry_points.txt
sbatchman-0.9.7.dist-info/top_level.txt
sbatchman-0.9.7.dist-info/RECORD
