Metadata-Version: 2.4
Name: sbatchman
Version: 0.9.7
Summary: A utility to create, launch and monitor code experiments on SLURM, PBS, or local machines.
Author: Lorenzo Pichetti
Author-email: Thomas Pasquali <thomas.pasquali@unitn.it>, Salvatore Andaloro <sbatchman@sasso.dev>
Project-URL: Homepage, https://github.com/LorenzoPichetti/SbatchMan
Project-URL: Bug Tracker, https://github.com/LorenzoPichetti/SbatchMan/issues
Classifier: Programming Language :: Python :: 3
Classifier: License :: OSI Approved :: MIT License
Classifier: Operating System :: OS Independent
Requires-Python: >=3.8
Requires-Dist: typer
Requires-Dist: textual
Requires-Dist: rich
Requires-Dist: PyYAML
Requires-Dist: platformdirs
Requires-Dist: pandas
